{
  "project_info": {
    "project_number": "874970821206",
    "project_id": "chat-project-2ea29",
    "storage_bucket": "chat-project-2ea29.appspot.com"
  },
  "client": [
    {
      "client_info": {
        "mobilesdk_app_id": "1:874970821206:android:16206c3b94c3275127c1f7",
        "android_client_info": {
          "package_name": "com.example.fit_i"
        }
      },
      "oauth_client": [
        {
          "client_id": "874970821206-t3k5vk2q6s75e8jf8795knuaibo1fnfi.apps.googleusercontent.com",
          "client_type": 3
        }
      ],
      "api_key": [
        {
          "current_key": "AIzaSyBUmMCGteOAwIDmG9K79WScOBY_2FnCvso"
        }
      ],
      "services": {
        "appinvite_service": {
          "other_platform_oauth_client": [
            {
              "client_id": "874970821206-t3k5vk2q6s75e8jf8795knuaibo1fnfi.apps.googleusercontent.com",
              "client_type": 3
            }
          ]
        }
      }
    }
  ],
  "configuration_version": "1"
}